Workbook

Sheet Негативы
A1: Отрицательные примеры к датасету организаторов: мейнстрим, хайп, шум
A2: Формат повторяет файл организаторов, добавлены колонка «Класс» и числовые шкалы. Все ссылки открыты и проверены 29 сентября 2026 года. Колонку «Почему не слабый сигнал» модели на вход не подавать: в ней содержится ответ.
A4: № | B4: Технология | C4: Область | D4: Класс | E4: Компании | F4: Почему не слабый сигнал | G4: Стадия развития | H4: Стадия (0–5) | I4: Тренд упоминаний | J4: Динамика (−1…3) | K4: Балл (стадия + динамика) | L4: Источники
A5: 1 | B5: Машинное зрение для контроля качества на конвейере | C5: Индустриальный ИИ | D5: Мейнстрим | E5: Cognex, Keyence, Basler, Datalogic | F5: Рынок сформирован десятилетия назад: уже в 2006 году только в Северной Америке он оценивался в $1,5 млрд. Есть отраслевые ассоциации (AIA, EMVA) и интерфейсные стандарты Camera Link и CoaXPress, есть явные лидеры. | G5: Массовое внедрение | H5: 5 | I5: Стабильный: технология давно в производстве, растёт только доля нейросетевых моделей внутри неё | J5: 0 | K5: =H5+J5 -> 5 | L5: [Machine vision (Wikipedia)](https://en.wikipedia.org/wiki/Machine_vision)
A6: 2 | B6: SCADA-системы диспетчерского управления | C6: Индустриальный ИИ | D6: Мейнстрим | E6: Siemens (WinCC), AVEVA (Wonderware), Rockwell Automation, Schneider Electric | F6: Отраслевой стандарт де-факто с прописанными протоколами: IEC 61131-3, IEC 60870-5, DNP3. С 1998 года все крупные производители ПЛК поставляют интегрированные HMI/SCADA, технология стоит в энергетике, нефтегазе и водоснабжении. | G6: Массовое внедрение, отраслевой стандарт | H6: 5 | I6: Стабильный: обсуждается в контексте кибербезопасности, а не новизны | J6: 0 | K6: =H6+J6 -> 5 | L6: [SCADA (Wikipedia)](https://en.wikipedia.org/wiki/SCADA)
A7: 3 | B7: MES — системы управления производством | C7: Индустриальный ИИ | D7: Мейнстрим | E7: Siemens Opcenter, AVEVA, SAP, Dassault Systèmes | F7: Архитектура закреплена стандартом ANSI/ISA-95 ещё в 2000 году и уточнялась до 2013-го. Категория существует с 1990-х, рынок поделён между крупными вендорами ERP и АСУ ТП. | G7: Массовое внедрение, отраслевой стандарт | H7: 5 | I7: Стабильный: новизна только в переезде в облако | J7: 0 | K7: =H7+J7 -> 5 | L7: [Manufacturing execution system (Wikipedia)](https://en.wikipedia.org/wiki/Manufacturing_execution_system)
A8: 4 | B8: OPC UA как протокол промышленной связности | C8: Индустриальный ИИ | D8: Мейнстрим | E8: OPC Foundation, Siemens, Beckhoff, Rockwell Automation | F8: Открытый стандарт IEC 62541 опубликован 28 июля 2006 года, поддерживается более чем 60 типами промышленного оборудования, реализации есть на всех популярных языках. Это инфраструктурный слой, а не зарождающийся рынок. | G8: Отраслевой стандарт | H8: 5 | I8: Стабильный: обсуждается как требование к оборудованию | J8: 0 | K8: =H8+J8 -> 5 | L8: [OPC Unified Architecture (Wikipedia)](https://en.wikipedia.org/wiki/OPC_Unified_Architecture)
A9: 5 | B9: Промышленные роботы-манипуляторы | C9: Индустриальный ИИ | D9: Мейнстрим | E9: ABB, KUKA, FANUC, Yaskawa, Comau | F9: По данным Международной федерации робототехники, в 2024 году в мире работало около 4,66 млн промышленных роботов. Рынок поделён между несколькими производителями, безопасность закреплена отраслевыми стандартами. | G9: Массовое внедрение | H9: 5 | I9: Стабильный: колебания вместе с инвестициями в производство | J9: 0 | K9: =H9+J9 -> 5 | L9: [Industrial robot (Wikipedia)](https://en.wikipedia.org/wiki/Industrial_robot)
A10: 6 | B10: Предиктивное обслуживание оборудования | C10: Индустриальный ИИ | D10: Мейнстрим | E10: SKF, Siemens, GE Vernova, Bosch Rexroth | F10: Практика описана в учебниках и внедряется с 2000-х: например, горнодобывающая Boliden развернула комплексное решение ещё в 2010 году. Передача данных опирается на устоявшиеся протоколы HART, IEC 61850, OLE. | G10: Массовое внедрение | H10: 5 | I10: Стабильный: спрос ровный, новизна только в отдельных подходах внутри | J10: 0 | K10: =H10+J10 -> 5 | L10: [Predictive maintenance (Wikipedia)](https://en.wikipedia.org/wiki/Predictive_maintenance)
A11: 7 | B11: Коллаборативные роботы (коботы) | C11: Роботы | D11: Мейнстрим | E11: Universal Robots, Techman Robot, FANUC, Doosan Robotics | F11: Категория изобретена в 1996 году, а требования закреплены стандартом ISO/TS 15066:2016. Рынок сформирован, продаётся серийно через интеграторов, у покупателей есть бюджетная строка. | G11: Массовое внедрение, есть стандарт | H11: 5 | I11: Стабильный: обсуждается как оборудование, а не как новость | J11: 0 | K11: =H11+J11 -> 5 | L11: [Cobot (Wikipedia)](https://en.wikipedia.org/wiki/Cobot)
A12: 8 | B12: Складские транспортные роботы AGV и AMR | C12: Роботы | D12: Мейнстрим | E12: Amazon Robotics, Geek+, DHL, Swisslog | F12: Первый AGV вышел на рынок в 1950-х, в порту Роттердама автоматические тележки работают с 1993 года. Сегодня это стандартная часть распределительных центров, а не ранний рынок. | G12: Массовое внедрение | H12: 5 | I12: Стабильный: новости про конкретные контракты, а не про технологию | J12: 0 | K12: =H12+J12 -> 5 | L12: [Automated guided vehicle (Wikipedia)](https://en.wikipedia.org/wiki/Automated_guided_vehicle)
A13: 9 | B13: Бытовые роботы-пылесосы | C13: Роботы | D13: Мейнстрим | E13: iRobot, Roborock, Ecovacs, Dreame | F13: Массовый рынок с 2002 года, когда вышел Roomba; к 2021 году iRobot заявляла о более чем 40 млн проданных устройств. Категория потребительская, с ценовой конкуренцией и явными лидерами. | G13: Массовое внедрение | H13: 5 | I13: Стабильный: обсуждаются модели и цены, а не технология | J13: 0 | K13: =H13+J13 -> 5 | L13: [Robotic vacuum cleaner (Wikipedia)](https://en.wikipedia.org/wiki/Robotic_vacuum_cleaner)
A14: 10 | B14: Хирургические роботы da Vinci | C14: Роботы | D14: Мейнстрим | E14: Intuitive Surgical | F14: Система применяется в клиниках с 2000 года, по данным 2012 года с её помощью проведено около 200 тысяч операций. Рынок сформирован, есть один явный лидер и регуляторные допуски. | G14: Массовое внедрение | H14: 5 | I14: Стабильный: обсуждается стоимость и конкуренты, а не новизна | J14: 0 | K14: =H14+J14 -> 5 | L14: [da Vinci Surgical System (Wikipedia)](https://en.wikipedia.org/wiki/Da_Vinci_Surgical_System)
A15: 11 | B15: ROS как программная платформа для роботов | C15: Роботы | D15: Мейнстрим | E15: Open Robotics, NVIDIA, Bosch, Amazon Web Services | F15: Открытая платформа существует с 2007 года, с 2013-го её развитием занимается Open Robotics. Это инфраструктурный слой, на котором строят решения, а не самостоятельный зарождающийся рынок. | G15: Отраслевой стандарт де-факто | H15: 5 | I15: Стабильный: обсуждаются версии и миграция на ROS 2 | J15: 0 | K15: =H15+J15 -> 5 | L15: [Robot Operating System (Wikipedia)](https://en.wikipedia.org/wiki/Robot_Operating_System)
A16: 12 | B16: Kubernetes для оркестрации нагрузок | C16: Инфраструктура ИИ | D16: Мейнстрим | E16: CNCF, Google, Red Hat, Amazon Web Services, Microsoft | F16: Проект вышел в 2014 году, с 2015-го развивается под CNCF, а в 2017-м все крупные облака добавили нативную поддержку. Это стандарт де-факто, на котором запускают в том числе обучение моделей. | G16: Отраслевой стандарт де-факто | H16: 5 | I16: Стабильный: обсуждаются надстройки, а не сама технология | J16: 0 | K16: =H16+J16 -> 5 | L16: [Kubernetes (Wikipedia)](https://en.wikipedia.org/wiki/Kubernetes)
... A57: 53 | B57: Тег-лента новостей по теме вместо статьи | C57: Роботы | D57: Шум | E57: Площадка Robots Atlas | F57: Ссылка ведёт на рубрику сайта, а не на конкретный материал: содержимое меняется каждый день, проверить утверждение по ней невозможно. Такие адреса нельзя класть в выдачу как источник. | G57: Не технология: рубрика сайта | H57: 0 | I57: Лента обновляется ежедневно | J57: 1 | K57: =H57+J57 -> 1 | L57: [Тег «tactile sensing» (Robots Atlas)](https://robotsatlas.com/tags/tactile-sensing)

Sheet Сводка
A1: Состав файла
A3: Область | B3: Мейнстрим | C3: Хайп | D3: Шум | E3: Всего
A4: Индустриальный ИИ | B4: =COUNTIFS(Негативы!$C$5:$C$57,$A4,Негативы!$D$5:$D$57,B$3) -> 6 | C4: =COUNTIFS(Негативы!$C$5:$C$57,$A4,Негативы!$D$5:$D$57,C$3) -> 1 | D4: =COUNTIFS(Негативы!$C$5:$C$57,$A4,Негативы!$D$5:$D$57,D$3) -> 2 | E4: =SUM(B4:D4) -> 9
A5: Роботы | B5: =COUNTIFS(Негативы!$C$5:$C$57,$A5,Негативы!$D$5:$D$57,B$3) -> 5 | C5: =COUNTIFS(Негативы!$C$5:$C$57,$A5,Негативы!$D$5:$D$57,C$3) -> 2 | D5: =COUNTIFS(Негативы!$C$5:$C$57,$A5,Негативы!$D$5:$D$57,D$3) -> 1 | E5: =SUM(B5:D5) -> 8
A6: Инфраструктура ИИ | B6: =COUNTIFS(Негативы!$C$5:$C$57,$A6,Негативы!$D$5:$D$57,B$3) -> 6 | C6: =COUNTIFS(Негативы!$C$5:$C$57,$A6,Негативы!$D$5:$D$57,C$3) -> 4 | D6: =COUNTIFS(Негативы!$C$5:$C$57,$A6,Негативы!$D$5:$D$57,D$3) -> 2 | E6: =SUM(B6:D6) -> 12
A7: Финтех | B7: =COUNTIFS(Негативы!$C$5:$C$57,$A7,Негативы!$D$5:$D$57,B$3) -> 5 | C7: =COUNTIFS(Негативы!$C$5:$C$57,$A7,Негативы!$D$5:$D$57,C$3) -> 2 | D7: =COUNTIFS(Негативы!$C$5:$C$57,$A7,Негативы!$D$5:$D$57,D$3) -> 1 | E7: =SUM(B7:D7) -> 8
A8: Защита ИИ | B8: =COUNTIFS(Негативы!$C$5:$C$57,$A8,Негативы!$D$5:$D$57,B$3) -> 6 | C8: =COUNTIFS(Негативы!$C$5:$C$57,$A8,Негативы!$D$5:$D$57,C$3) -> 0 | D8: =COUNTIFS(Негативы!$C$5:$C$57,$A8,Негативы!$D$5:$D$57,D$3) -> 2 | E8: =SUM(B8:D8) -> 8
A9: Edge | B9: =COUNTIFS(Негативы!$C$5:$C$57,$A9,Негативы!$D$5:$D$57,B$3) -> 6 | C9: =COUNTIFS(Негативы!$C$5:$C$57,$A9,Негативы!$D$5:$D$57,C$3) -> 2 | D9: =COUNTIFS(Негативы!$C$5:$C$57,$A9,Негативы!$D$5:$D$57,D$3) -> 0 | E9: =SUM(B9:D9) -> 8
A10: Всего | B10: =SUM(B4:B9) -> 34 | C10: =SUM(C4:C9) -> 11 | D10: =SUM(D4:D9) -> 8 | E10: =SUM(E4:E9) -> 53
A12: Средняя стадия по классам | B12: стадия | C12: динамика
A13: Мейнстрим | B13: =ROUND(AVERAGEIF(Негативы!$D$5:$D$57,A13,Негативы!$H$5:$H$57),1) -> 5 | C13: =ROUND(AVERAGEIF(Негативы!$D$5:$D$57,A13,Негативы!$J$5:$J$57),1) -> 0.1
A14: Хайп | B14: =ROUND(AVERAGEIF(Негативы!$D$5:$D$57,A14,Негативы!$H$5:$H$57),1) -> 1.4 | C14: =ROUND(AVERAGEIF(Негативы!$D$5:$D$57,A14,Негативы!$J$5:$J$57),1) -> -0.6
A15: Шум | B15: =ROUND(AVERAGEIF(Негативы!$D$5:$D$57,A15,Негативы!$H$5:$H$57),1) -> 0 | C15: =ROUND(AVERAGEIF(Негативы!$D$5:$D$57,A15,Негативы!$J$5:$J$57),1) -> 1.6
A17: Читается так: у мейнстрима высокая стадия и нулевая динамика, у хайпа низкая стадия при заметной медийной активности, у шума стадии нет вообще. Датасет организаторов занимает полосу между ними: стадия от 1 до 4 при растущей динамике.

Sheet Как размечали
A1: Протокол разметки
A3: Зачем этот файл | B3: В датасете организаторов 100 строк, и все они — слабые сигналы. Модели не с чем сравнивать: она не видела ни зрелых технологий, ни хайпа, ни информационного шума. Эти 53 строки достраивают вторую сторону границы. Формат колонок повторяет их файл, чтобы признаки считались одинаково.
A4: Класс «Мейнстрим» (34 строки) | B4: Массовое внедрение, сформированный рынок, явные лидеры или отраслевой стандарт. Проверка простая: есть ли у технологии стандарт (ISO, IEC, IEEE, RFC, ANSI/ISA), известны ли лидеры рынка и есть ли у покупателей бюджетная строка. По ТЗ такие технологии в выдачу не попадают.
A5: Класс «Хайп» (11 строк) | B5: Медийная активность намного выше реальной стадии: много прессы и обещаний, мало внедрений, а в части случаев — отменённые продукты и закрытые компании. В каждой строке указаны конкретные цифры разрыва: сколько собрали, сколько продали, когда закрылись.
A6: Класс «Шум» (8 строк) | B6: Документы, которые пайплайн принимает за кандидата, хотя технологии в них нет: подборки-рейтинги, SEO-статьи с продажей курсов, прогнозы рынка без методологии, карточки компаний в каталогах, тег-ленты сайтов. Две последние строки взяты из источников самого датасета организаторов.
A7: Где проходит граница | B7: Границу проводим по разметке организаторов, а не по своему мнению. Если технология похожа на их позитив, в негативы она не идёт. Их верхняя граница — «раннее внедрение»; всё, что дошло до массового внедрения или стало стандартом, попадает сюда. Пограничные строки в файле: NPU в смартфонах (их №16 про NPU в микроконтроллерах), память HBM, распознавание лиц, коботы.
A8: Шкалы | B8: Стадия: 0 — не технология, 1 — концепция или закрытый проект, 2 — прототип, 3 — пилот, 4 — раннее внедрение, 5 — массовое внедрение или стандарт. Динамика: −1 снижается, 0 стабильно, 1 растёт медленно, 2 растёт, 3 растёт быстро. Балл считается той же формулой, что у организаторов (стадия плюс динамика), чтобы шкалы стыковались; для класса «Шум» балл смысла не имеет.
A9: Чего не подавать модели | B9: Колонку «Почему не слабый сигнал» — в ней прямо назван ответ. Названия площадок в колонке «Источники» — только их тип и уровень доверия. Длину текстов тоже стоит проверить: если ваши строки заметно отличаются от строк организаторов по длине и лексике, модель научится различать авторов, а не классы.
A10: Источники | B10: Для мейнстрима использованы энциклопедические статьи как маркер зрелости: в них видно год появления технологии, стандарты и лидеров рынка. В тексте каждой строки назван сам стандарт (ISO/TS 15066, IEC 62541, ANSI/ISA-95, RFC 8446, ISO/IEC 14443 и другие) — к финальной сдаче их лучше заменить ссылками на первоисточники. Все ссылки открыты и проверены 29 сентября 2026 года.
A11: Что доделать | B11: Довести до 100–150 строк, сохраняя пропорцию: около двух третей мейнстрима, остальное — хайп и шум; треть строк сделать пограничными. Затем 30 строк вслепую разметить вторым человеком и сверить расхождения — это и будет обоснование методологии для жюри.
